{
  "project_info": {
    "project_number": "26251006766",
    "project_id": "flutter-chat-ad97c",
    "storage_bucket": "flutter-chat-ad97c.appspot.com"
  },
  "client": [
    {
      "client_info": {
        "mobilesdk_app_id": "1:26251006766:android:b2789ac6a2a692ca17e0bf",
        "android_client_info": {
          "package_name": "com.example.chat_app"
        }
      },
      "oauth_client": [],
      "api_key": [
        {
          "current_key": "AIzaSyBFTrhT4Qhfe9D3RDnGhBk0xFLRWDV2Wfo"
        }
      ],
      "services": {
        "appinvite_service": {
          "other_platform_oauth_client": []
        }
      }
    }
  ],
  "configuration_version": "1"
}